Workbook

Sheet Charter
B2: INTELA – SILVERFIN INTEGRATION · 24-MONTH PROGRAMME MANAGEMENT PLAN
B3: Deloitte Africa | Tax Technology · South Africa · Nigeria · Ghana · Kenya · Tanzania · Uganda · CONFIDENTIAL — internal planning document
B5: PROGRAMME CONTROL
B6: Programme | D6: Deloitte Africa — Intela–Silverfin Integration Programme
B7: Sponsor | D7: Deloitte Africa Tax & Legal Technology Leadership (to confirm)
B8: Programme Manager | D8: To be appointed
B9: Prepared by | D9: Tochukwu (El Tee) Owunwanne — Tax Technology, Deloitte Nigeria
B10: PMO contact | D10: Sharon Norambuena — Senior Manager: Africa Tax & Legal, Intela PMO
B11: Programme start date | D11: 46327
B12: Programme end date | D12: =IF(Charter!$D$11="","",EDATE(Charter!$D$11,24)-1) -> 47057
B13: Desired deployment date | D13: As soon as the integration is approved for use — aligned to each country's Intela deployment plan
B14: Busy season constraint | D14: Not applicable
B15: Version / date | D15: v2.0 · September 2026
B16: ◄ The yellow cell above is the only date you edit. Every start date, finish date, month column and milestone date in this workbook is calculated from it.
B18: PROGRAMME CHARTER
B19: Background | D19: Tax practitioners across Deloitte Africa currently move documents, status updates and trial balances between Intela and Silverfin manually, running duplicate workflows with no unified view. This programme establishes a two-way integration so that data captured in Intela flows to Silverfin and back, removing manual effort and creating a single, reliable engagement view.
B23: Objectives | D23: 1. Deliver bi-directional trial balance and general ledger synchronisation via the Silverfin SyncAPI. 2. Synchronise documents, engagement status, comments and to-do items between the two platforms. 3. Automate event-based workflows and provide end-to-end monitoring and audit. 4. Roll the solution out across six African countries on a controlled, wave-based schedule.
B28: Scope — in | D28: Client and engagement sync · Trial balance and GL sync · Document sync · Status sync · Comments and to-do sync · Workflow automation · Monitoring and audit · Multi-country configuration and rollout across six countries.
B31: Scope — out | D31: Changes to core Intela or Silverfin product code · Migration of historical archives beyond an agreed cut-off · New tax-computation logic (delivered separately) · Countries outside the six named markets.
B34: Delivery approach | D34: Five stages, applied per region: (1) assessment of tools and build, (2) document sign-off from all stakeholders, (3) architectural build, (4) UAT, (5) deployment. Build runs M1–M19 centrally; UAT and deployment run per region in three waves from M18.
B37: Success criteria | D37: Zero manual TB uploads for onboarded engagements · Documents and status reconcile automatically within SLA · A single unified engagement view for practitioners · Successful go-live in all six countries with hypercare exit met.
B40: Indicative effort | D40: MVP 12–16 weeks · enterprise build 6–9 months · full multi-country programme up to 24 months. Budget to be confirmed after technical discovery and SyncAPI licensing clarification.
B43: Governance | D43: Programme Director / Sponsor · Programme Manager · Solution Architect · Integration Lead · Country SMEs (×6) · Security & Compliance Lead · QA Lead · Change / Training Lead. The steering committee reviews at each phase gate.
B46: Constraints & assumptions | D46: Dependent on Silverfin SyncAPI access and the Intela Integration Agent (see the Dependencies tab). Country SMEs available part-time throughout. Data residency and privacy addressed per jurisdiction.
B50: PROGRAMME STATUS — calculated from the Project Plan, Milestones and Risks tabs
B51: Tasks in plan | C51: Completed | D51: In progress | E51: Not started | F51: At risk / on hold | G51: Milestones met | H51: High risks open
B52: =COUNTA('Project Plan'!$E$7:$E$76) -> 70 | C52: =COUNTIF('Project Plan'!$P$7:$P$76,"Completed") -> 0 | D52: =COUNTIF('Project Plan'!$P$7:$P$76,"In progress") -> 0 | E52: =COUNTIF('Project Plan'!$P$7:$P$76,"Not started") -> 70 | F52: =COUNTIF('Project Plan'!$P$7:$P$76,"At risk")+COUNTIF('Project Plan'!$P$7:$P$76,"On hold") -> 0 | G52: =COUNTIF(Milestones!$H$7:$H$21,"Completed") -> 0 | H52: =COUNTIFS(Risks!$G$8:$G$22,">=15",Risks!$J$8:$J$22,"<>Closed") -> 6
B54: Added in this version: a dedicated 'Documentation & sign-off' phase (3.1–3.5) and a separate UAT phase per region (12.1–12.4), so the workbook follows the agreed five-step regional approach. Deployment is now its own phase (13.1–13.7).

Sheet Project Plan
B2: PROJECT MANAGEMENT PLAN · INTELA – SILVERFIN INTEGRATION
B3: Milestone → phase → sub-scope. Dates are calculated from the programme start date on the Charter tab.
L5: RESPONSIBILITY
B6: Milestone | C6: Project phase | D6: WBS | E6: Sub-scope / task | F6: Owner (role) | G6: Dependencies | H6: Mo. | I6: Dur. | J6: Start date | K6: End date | L6: Deloitte Tax Technology | M6: Intela PMO / Product | N6: Silverfin (vendor) | O6: Country practice / SMEs | P6: Status | Q6: Key deliverable / comments | R6: Phase key (helper — do not delete)
B7: 1. Assessment of tools / build per region | C7: 1. Africa Assessment | D7: 1.1 | E7: Programme mobilisation & governance set-up | F7: Programme Manager | G7: — | H7: 1 | I7: 1 | J7: =EDATE(Charter!$D$11,$H7-1) -> 46327 | K7: =EDATE(Charter!$D$11,$H7-1+$I7)-1 -> 46356 | L7: ✓ | M7: ✓ | P7: Not started | Q7: Governance model & charter | R7: 1. Africa Assessment
D8: 1.2 | E8: Stakeholder mapping across the six countries | F8: Business Analyst | G8: 1.1 | H8: 1 | I8: 1 | J8: =EDATE(Charter!$D$11,$H8-1) -> 46327 | K8: =EDATE(Charter!$D$11,$H8-1+$I8)-1 -> 46356 | L8: ✓ | O8: ✓ | P8: Not started | Q8: Stakeholder register | R8: 1. Africa Assessment
D9: 1.3 | E9: Current-state (as-is) process assessment | F9: Business Analyst | G9: 1.1 | H9: 1 | I9: 2 | J9: =EDATE(Charter!$D$11,$H9-1) -> 46327 | K9: =EDATE(Charter!$D$11,$H9-1+$I9)-1 -> 46387 | L9: ✓ | O9: ✓ | P9: Not started | Q9: As-is process maps | R9: 1. Africa Assessment
D10: 1.4 | E10: Country tax-compliance requirements catalogue | F10: Country SMEs | G10: 1.2 | H10: 2 | I10: 2 | J10: =EDATE(Charter!$D$11,$H10-1) -> 46357 | K10: =EDATE(Charter!$D$11,$H10-1+$I10)-1 -> 46418 | L10: ✓ | O10: ✓ | P10: Not started | Q10: Requirements catalogue | R10: 1. Africa Assessment
D11: 1.5 | E11: Silverfin footprint & licensing assessment per region | F11: Solution Architect | G11: 1.3 | H11: 2 | I11: 1 | J11: =EDATE(Charter!$D$11,$H11-1) -> 46357 | K11: =EDATE(Charter!$D$11,$H11-1+$I11)-1 -> 46387 | L11: ✓ | N11: ✓ | P11: Not started | Q11: Footprint & licensing report | R11: 1. Africa Assessment
D12: 1.6 | E12: Assessment report & prioritisation (GATE) | F12: Programme Manager | G12: 1.4,1.5 | H12: 3 | I12: 1 | J12: =EDATE(Charter!$D$11,$H12-1) -> 46388 | K12: =EDATE(Charter!$D$11,$H12-1+$I12)-1 -> 46418 | L12: ✓ | M12: ✓ | O12: ✓ | P12: Not started | Q12: Assessment sign-off | R12: 1. Africa Assessment
C13: 2. Technical Discovery | D13: 2.1 | E13: Silverfin API capability review | F13: Solution Architect | G13: 1.5 | H13: 2 | I13: 2 | J13: =EDATE(Charter!$D$11,$H13-1) -> 46357 | K13: =EDATE(Charter!$D$11,$H13-1+$I13)-1 -> 46418 | L13: ✓ | N13: ✓ | P13: Not started | Q13: API capability matrix | R13: 2. Technical Discovery
D14: 2.2 | E14: SyncAPI access request & validation (TB / GL) | F14: Integration Lead | G14: 1.1 | H14: 2 | I14: 2 | J14: =EDATE(Charter!$D$11,$H14-1) -> 46357 | K14: =EDATE(Charter!$D$11,$H14-1+$I14)-1 -> 46418 | L14: ✓ | N14: ✓ | P14: Not started | Q14: SyncAPI access confirmed | R14: 2. Technical Discovery
D15: 2.3 | E15: Intela Integration Agent assessment | F15: Integration Lead | G15: 2.1 | H15: 3 | I15: 1 | J15: =EDATE(Charter!$D$11,$H15-1) -> 46388 | K15: =EDATE(Charter!$D$11,$H15-1+$I15)-1 -> 46418 | L15: ✓ | M15: ✓ | P15: Not started | Q15: Agent assessment note | R15: 2. Technical Discovery
D16: 2.4 | E16: India CTR reference-architecture review | F16: Solution Architect | G16: 2.1 | H16: 3 | I16: 1 | J16: =EDATE(Charter!$D$11,$H16-1) -> 46388 | K16: =EDATE(Charter!$D$11,$H16-1+$I16)-1 -> 46418 | L16: ✓ | M16: ✓ | P16: Not started | Q16: Reference-pattern report | R16: 2. Technical Discovery
D17: 2.5 | E17: TB / Comments / To-Do API validation spike | F17: Integration Engineer | G17: 2.1 | H17: 3 | I17: 2 | J17: =EDATE(Charter!$D$11,$H17-1) -> 46388 | K17: =EDATE(Charter!$D$11,$H17-1+$I17)-1 -> 46446 | L17: ✓ | N17: ✓ | P17: Not started | Q17: Validation findings | R17: 2. Technical Discovery
D18: 2.6 | E18: Target architecture & security design (GATE) | F18: Solution Architect | G18: 2.2,2.3,2.5 | H18: 4 | I18: 1 | J18: =EDATE(Charter!$D$11,$H18-1) -> 46419 | K18: =EDATE(Charter!$D$11,$H18-1+$I18)-1 -> 46446 | L18: ✓ | M18: ✓ | P18: Not started | Q18: Architecture baseline | R18: 2. Technical Discovery
B19: 2. Document sign-off from all stakeholders | C19: 3. Documentation & Sign-off | D19: 3.1 | E19: Business requirements document per region | F19: Business Analyst | G19: 1.6,2.6 | H19: 4 | I19: 2 | J19: =EDATE(Charter!$D$11,$H19-1) -> 46419 | K19: =EDATE(Charter!$D$11,$H19-1+$I19)-1 -> 46477 | L19: ✓ | O19: ✓ | P19: Not started | Q19: BRD per country | R19: 3. Documentation & Sign-off
D20: 3.2 | E20: Functional & technical specification (solution design) | F20: Solution Architect | G20: 2.6 | H20: 5 | I20: 2 | J20: =EDATE(Charter!$D$11,$H20-1) -> 46447 | K20: =EDATE(Charter!$D$11,$H20-1+$I20)-1 -> 46507 | L20: ✓ | M20: ✓ | P20: Not started | Q20: FSD / solution design document | R20: 3. Documentation & Sign-off
D21: 3.3 | E21: Data-privacy & residency assessment pack (POPIA, NDPA, DPAs) | F21: Security Lead | G21: 3.1 | H21: 5 | I21: 1 | J21: =EDATE(Charter!$D$11,$H21-1) -> 46447 | K21: =EDATE(Charter!$D$11,$H21-1+$I21)-1 -> 46477 | L21: ✓ | O21: ✓ | P21: Not started | Q21: DPIA pack per jurisdiction | R21: 3. Documentation & Sign-off
D22: 3.4 | E22: Integration approval & security review (Intela & Silverfin) | F22: Integration Lead | G22: 3.2 | H22: 6 | I22: 1 | J22: =EDATE(Charter!$D$11,$H22-1) -> 46478 | K22: =EDATE(Charter!$D$11,$H22-1+$I22)-1 -> 46507 | L22: ✓ | M22: ✓ | N22: ✓ | P22: Not started | Q22: Vendor integration approval | R22: 3. Documentation & Sign-off
D23: 3.5 | E23: Stakeholder document sign-off — all six countries (GATE) | F23: Programme Manager | G23: 3.3,3.4 | H23: 6 | I23: 1 | J23: =EDATE(Charter!$D$11,$H23-1) -> 46478 | K23: =EDATE(Charter!$D$11,$H23-1+$I23)-1 -> 46507 | L23: ✓ | M23: ✓ | O23: ✓ | P23: Not started | Q23: Signed-off documentation set | R23: 3. Documentation & Sign-off
B24: 3. Architectural build per region | C24: 4. Foundation Integration Layer | D24: 4.1 | E24: Environment provisioning (dev / test / UAT / prod) | F24: DevOps Engineer | G24: 2.6 | H24: 4 | I24: 1 | J24: =EDATE(Charter!$D$11,$H24-1) -> 46419 | K24: =EDATE(Charter!$D$11,$H24-1+$I24)-1 -> 46446 | L24: ✓ | P24: Not started | Q24: Environments live | R24: 4. Foundation Integration Layer
D25: 4.2 | E25: Integration Agent deployment & configuration | F25: Integration Lead | G25: 2.6 | H25: 4 | I25: 2 | J25: =EDATE(Charter!$D$11,$H25-1) -> 46419 | K25: =EDATE(Charter!$D$11,$H25-1+$I25)-1 -> 46477 | L25: ✓ | M25: ✓ | P25: Not started | Q25: Agent deployed | R25: 4. Foundation Integration Layer
D26: 4.3 | E26: Authentication, authorisation & secrets management | F26: Security Lead | G26: 4.1 | H26: 5 | I26: 2 | J26: =EDATE(Charter!$D$11,$H26-1) -> 46447 | K26: =EDATE(Charter!$D$11,$H26-1+$I26)-1 -> 46507 | L26: ✓ | M26: ✓ | P26: Not started | Q26: Auth & vault ready | R26: 4. Foundation Integration Layer
D27: 4.4 | E27: Event bus / messaging framework | F27: Integration Engineer | G27: 4.1 | H27: 5 | I27: 2 | J27: =EDATE(Charter!$D$11,$H27-1) -> 46447 | K27: =EDATE(Charter!$D$11,$H27-1+$I27)-1 -> 46507 | L27: ✓ | P27: Not started | Q27: Messaging framework | R27: 4. Foundation Integration Layer
D28: 4.5 | E28: Core Silverfin connector (companies / periods / users) | F28: Integration Engineer | G28: 4.3,4.4 | H28: 6 | I28: 2 | J28: =EDATE(Charter!$D$11,$H28-1) -> 46478 | K28: =EDATE(Charter!$D$11,$H28-1+$I28)-1 -> 46538 | L28: ✓ | N28: ✓ | P28: Not started | Q28: Connector v1 | R28: 4. Foundation Integration Layer
D29: 4.6 | E29: Error handling, retry & logging framework | F29: Integration Engineer | G29: 4.5 | H29: 7 | I29: 1 | J29: =EDATE(Charter!$D$11,$H29-1) -> 46508 | K29: =EDATE(Charter!$D$11,$H29-1+$I29)-1 -> 46538 | L29: ✓ | P29: Not started | Q29: Resilience framework | R29: 4. Foundation Integration Layer
D30: 4.7 | E30: CI/CD pipeline & infrastructure-as-code | F30: DevOps Engineer | G30: 4.1 | H30: 6 | I30: 2 | J30: =EDATE(Charter!$D$11,$H30-1) -> 46478 | K30: =EDATE(Charter!$D$11,$H30-1+$I30)-1 -> 46538 | L30: ✓ | P30: Not started | Q30: CI/CD pipeline | R30: 4. Foundation Integration Layer
D31: 4.8 | E31: Foundation layer integration test (GATE) | F31: QA Lead | G31: 4.5,4.7 | H31: 8 | I31: 1 | J31: =EDATE(Charter!$D$11,$H31-1) -> 46539 | K31: =EDATE(Charter!$D$11,$H31-1+$I31)-1 -> 46568 | L31: ✓ | P31: Not started | Q31: Foundation layer ready | R31: 4. Foundation Integration Layer
C32: 5. Client & Engagement Sync | D32: 5.1 | E32: Client / entity data-model mapping | F32: Data Specialist | G32: 4.5 | H32: 6 | I32: 2 | J32: =EDATE(Charter!$D$11,$H32-1) -> 46478 | K32: =EDATE(Charter!$D$11,$H32-1+$I32)-1 -> 46538 | L32: ✓ | N32: ✓ | P32: Not started | Q32: Mapping specification | R32: 5. Client & Engagement Sync
D33: 5.2 | E33: Client mapping & account-mapping lists | F33: Data Specialist | G33: 5.1 | H33: 7 | I33: 2 | J33: =EDATE(Charter!$D$11,$H33-1) -> 46508 | K33: =EDATE(Charter!$D$11,$H33-1+$I33)-1 -> 46568 | L33: ✓ | O33: ✓ | P33: Not started | Q33: Mapping lists | R33: 5. Client & Engagement Sync
D34: 5.3 | E34: User synchronisation | F34: Integration Engineer | G34: 4.5 | H34: 7 | I34: 1 | J34: =EDATE(Charter!$D$11,$H34-1) -> 46508 | K34: =EDATE(Charter!$D$11,$H34-1+$I34)-1 -> 46538 | L34: ✓ | M34: ✓ | P34: Not started | Q34: User sync build | R34: 5. Client & Engagement Sync
D35: 5.4 | E35: Engagement / period linkage | F35: Integration Engineer | G35: 5.2 | H35: 8 | I35: 1 | J35: =EDATE(Charter!$D$11,$H35-1) -> 46539 | K35: =EDATE(Charter!$D$11,$H35-1+$I35)-1 -> 46568 | L35: ✓ | M35: ✓ | P35: Not started | Q35: Period linkage | R35: 5. Client & Engagement Sync
D36: 5.5 | E36: Client & engagement sync testing (GATE) | F36: QA Lead | G36: 5.3,5.4 | H36: 9 | I36: 1 | J36: =EDATE(Charter!$D$11,$H36-1) -> 46569 | K36: =EDATE(Charter!$D$11,$H36-1+$I36)-1 -> 46599 | L36: ✓ | P36: Not started | Q36: Client sync complete | R36: 5. Client & Engagement Sync
C37: 6. Trial Balance & GL Integration | D37: 6.1 | E37: SyncAPI integration design (TB & GL) | F37: Solution Architect | G37: 2.2,4.8 | H37: 8 | I37: 1 | J37: =EDATE(Charter!$D$11,$H37-1) -> 46539 | K37: =EDATE(Charter!$D$11,$H37-1+$I37)-1 -> 46568 | L37: ✓ | N37: ✓ | P37: Not started | Q37: TB / GL design | R37: 6. Trial Balance & GL Integration
D38: 6.2 | E38: TB import mapping & transformation rules | F38: Data Specialist | G38: 5.2 | H38: 8 | I38: 2 | J38: =EDATE(Charter!$D$11,$H38-1) -> 46539 | K38: =EDATE(Charter!$D$11,$H38-1+$I38)-1 -> 46599 | L38: ✓ | O38: ✓ | P38: Not started | Q38: Transformation rules | R38: 6. Trial Balance & GL Integration
D39: 6.3 | E39: General Ledger synchronisation build | F39: Integration Engineer | G39: 6.1 | H39: 9 | I39: 2 | J39: =EDATE(Charter!$D$11,$H39-1) -> 46569 | K39: =EDATE(Charter!$D$11,$H39-1+$I39)-1 -> 46630 | L39: ✓ | N39: ✓ | P39: Not started | Q39: GL sync build | R39: 6. Trial Balance & GL Integration
D40: 6.4 | E40: TB push Intela → Silverfin build | F40: Integration Engineer | G40: 6.2,6.3 | H40: 10 | I40: 2 | J40: =EDATE(Charter!$D$11,$H40-1) -> 46600 | K40: =EDATE(Charter!$D$11,$H40-1+$I40)-1 -> 46660 | L40: ✓ | M40: ✓ | N40: ✓ | P40: Not started | Q40: TB sync build | R40: 6. Trial Balance & GL Integration
D41: 6.5 | E41: Account-mapping validation & reconciliation | F41: Data Specialist | G41: 6.4 | H41: 11 | I41: 1 | J41: =EDATE(Charter!$D$11,$H41-1) -> 46631 | K41: =EDATE(Charter!$D$11,$H41-1+$I41)-1 -> 46660 | L41: ✓ | O41: ✓ | P41: Not started | Q41: Reconciliation controls | R41: 6. Trial Balance & GL Integration
D42: 6.6 | E42: TB / GL end-to-end testing (GATE) | F42: QA Lead | G42: 6.4,6.5 | H42: 12 | I42: 1 | J42: =EDATE(Charter!$D$11,$H42-1) -> 46661 | K42: =EDATE(Charter!$D$11,$H42-1+$I42)-1 -> 46691 | L42: ✓ | P42: Not started | Q42: TB / GL validated | R42: 6. Trial Balance & GL Integration
C43: 7. Document Synchronisation | D43: 7.1 | E43: Document taxonomy & metadata mapping | F43: Business Analyst | G43: 5.5 | H43: 10 | I43: 1 | J43: =EDATE(Charter!$D$11,$H43-1) -> 46600 | K43: =EDATE(Charter!$D$11,$H43-1+$I43)-1 -> 46630 | L43: ✓ | O43: ✓ | P43: Not started | Q43: Document taxonomy | R43: 7. Document Synchronisation
D44: 7.2 | E44: Document sync build (documents, schedules, packs) | F44: Integration Engineer | G44: 7.1 | H44: 11 | I44: 2 | J44: =EDATE(Charter!$D$11,$H44-1) -> 46631 | K44: =EDATE(Charter!$D$11,$H44-1+$I44)-1 -> 46691 | L44: ✓ | M44: ✓ | P44: Not started | Q44: Document sync build | R44: 7. Document Synchronisation
D45: 7.3 | E45: Live Export Documents integration | F45: Integration Engineer | G45: 7.2 | H45: 12 | I45: 1 | J45: =EDATE(Charter!$D$11,$H45-1) -> 46661 | K45: =EDATE(Charter!$D$11,$H45-1+$I45)-1 -> 46691 | L45: ✓ | N45: ✓ | P45: Not started | Q45: Live export integrated | R45: 7. Document Synchronisation
D46: 7.4 | E46: Document versioning & retention rules | F46: Security Lead | G46: 7.2 | H46: 12 | I46: 1 | J46: =EDATE(Charter!$D$11,$H46-1) -> 46661 | K46: =EDATE(Charter!$D$11,$H46-1+$I46)-1 -> 46691 | L46: ✓ | P46: Not started | Q46: Versioning rules | R46: 7. Document Synchronisation
D47: 7.5 | E47: Document sync testing (GATE) | F47: QA Lead | G47: 7.3,7.4 | H47: 13 | I47: 1 | J47: =EDATE(Charter!$D$11,$H47-1) -> 46692 | K47: =EDATE(Charter!$D$11,$H47-1+$I47)-1 -> 46721 | L47: ✓ | P47: Not started | Q47: Document sync complete | R47: 7. Document Synchronisation
C48: 8. Status Synchronisation | D48: 8.1 | E48: Status model harmonisation | F48: Business Analyst | G48: 7.1 | H48: 12 | I48: 1 | J48: =EDATE(Charter!$D$11,$H48-1) -> 46661 | K48: =EDATE(Charter!$D$11,$H48-1+$I48)-1 -> 46691 | L48: ✓ | M48: ✓ | P48: Not started | Q48: Status model | R48: 8. Status Synchronisation
D49: 8.2 | E49: Status sync build (bi-directional) | F49: Integration Engineer | G49: 8.1 | H49: 13 | I49: 1 | J49: =EDATE(Charter!$D$11,$H49-1) -> 46692 | K49: =EDATE(Charter!$D$11,$H49-1+$I49)-1 -> 46721 | L49: ✓ | M49: ✓ | N49: ✓ | P49: Not started | Q49: Status sync build | R49: 8. Status Synchronisation
D50: 8.3 | E50: Webhook / event triggers for status | F50: Integration Engineer | G50: 8.2 | H50: 13 | I50: 1 | J50: =EDATE(Charter!$D$11,$H50-1) -> 46692 | K50: =EDATE(Charter!$D$11,$H50-1+$I50)-1 -> 46721 | L50: ✓ | P50: Not started | Q50: Event triggers | R50: 8. Status Synchronisation
D51: 8.4 | E51: Status sync testing (GATE) | F51: QA Lead | G51: 8.2,8.3 | H51: 14 | I51: 1 | J51: =EDATE(Charter!$D$11,$H51-1) -> 46722 | K51: =EDATE(Charter!$D$11,$H51-1+$I51)-1 -> 46752 | L51: ✓ | P51: Not started | Q51: Status sync complete | R51: 8. Status Synchronisation
C52: 9. Comments & To-Do Sync | D52: 9.1 | E52: Remarks / Comments API validation & mapping | F52: Integration Engineer | G52: 2.5 | H52: 13 | I52: 1 | J52: =EDATE(Charter!$D$11,$H52-1) -> 46692 | K52: =EDATE(Charter!$D$11,$H52-1+$I52)-1 -> 46721 | L52: ✓ | N52: ✓ | P52: Not started | Q52: Remarks mapping | R52: 9. Comments & To-Do Sync
D53: 9.2 | E53: Comments & review-notes sync build | F53: Integration Engineer | G53: 9.1 | H53: 14 | I53: 1 | J53: =EDATE(Charter!$D$11,$H53-1) -> 46722 | K53: =EDATE(Charter!$D$11,$H53-1+$I53)-1 -> 46752 | L53: ✓ | P53: Not started | Q53: Comments sync build | R53: 9. Comments & To-Do Sync
D54: 9.3 | E54: To-do / assignments sync build | F54: Integration Engineer | G54: 9.1 | H54: 14 | I54: 1 | J54: =EDATE(Charter!$D$11,$H54-1) -> 46722 | K54: =EDATE(Charter!$D$11,$H54-1+$I54)-1 -> 46752 | L54: ✓ | P54: Not started | Q54: To-do sync build | R54: 9. Comments & To-Do Sync
D55: 9.4 | E55: Comments & to-do testing (GATE) | F55: QA Lead | G55: 9.2,9.3 | H55: 15 | I55: 1 | J55: =EDATE(Charter!$D$11,$H55-1) -> 46753 | K55: =EDATE(Charter!$D$11,$H55-1+$I55)-1 -> 46783 | L55: ✓ | P55: Not started | Q55: Comments & to-do complete | R55: 9. Comments & To-Do Sync
C56: 10. Workflow Automation | D56: 10.1 | E56: Event-based automation-rules design | F56: Solution Architect | G56: 8.4 | H56: 14 | I56: 1 | J56: =EDATE(Charter!$D$11,$H56-1) -> 46722 | K56: =EDATE(Charter!$D$11,$H56-1+$I56)-1 -> 46752 | L56: ✓ | M56: ✓ | P56: Not started | Q56: Automation rules | R56: 10. Workflow Automation
D57: 10.2 | E57: Workflow orchestration build | F57: Integration Engineer | G57: 10.1 | H57: 15 | I57: 2 | J57: =EDATE(Charter!$D$11,$H57-1) -> 46753 | K57: =EDATE(Charter!$D$11,$H57-1+$I57)-1 -> 46812 | L57: ✓ | P57: Not started | Q57: Orchestration build | R57: 10. Workflow Automation
D58: 10.3 | E58: Cross-platform workflow triggers | F58: Integration Engineer | G58: 10.2 | H58: 16 | I58: 1 | J58: =EDATE(Charter!$D$11,$H58-1) -> 46784 | K58: =EDATE(Charter!$D$11,$H58-1+$I58)-1 -> 46812 | L58: ✓ | M58: ✓ | N58: ✓ | P58: Not started | Q58: Cross-platform triggers | R58: 10. Workflow Automation
D59: 10.4 | E59: Exception & escalation handling | F59: Integration Engineer | G59: 10.2 | H59: 16 | I59: 1 | J59: =EDATE(Charter!$D$11,$H59-1) -> 46784 | K59: =EDATE(Charter!$D$11,$H59-1+$I59)-1 -> 46812 | L59: ✓ | P59: Not started | Q59: Exception handling | R59: 10. Workflow Automation
D60: 10.5 | E60: Workflow automation testing (GATE) | F60: QA Lead | G60: 10.3,10.4 | H60: 17 | I60: 1 | J60: =EDATE(Charter!$D$11,$H60-1) -> 46813 | K60: =EDATE(Charter!$D$11,$H60-1+$I60)-1 -> 46843 | L60: ✓ | P60: Not started | Q60: Workflow automation complete | R60: 10. Workflow Automation
C61: 11. Monitoring & Audit | D61: 11.1 | E61: Monitoring & observability dashboards | F61: DevOps Engineer | G61: 10.2 | H61: 16 | I61: 2 | J61: =EDATE(Charter!$D$11,$H61-1) -> 46784 | K61: =EDATE(Charter!$D$11,$H61-1+$I61)-1 -> 46843 | L61: ✓ | P61: Not started | Q61: Dashboards | R61: 11. Monitoring & Audit
D62: 11.2 | E62: Audit trail & compliance logging | F62: Security Lead | G62: 11.1 | H62: 17 | I62: 2 | J62: =EDATE(Charter!$D$11,$H62-1) -> 46813 | K62: =EDATE(Charter!$D$11,$H62-1+$I62)-1 -> 46873 | L62: ✓ | P62: Not started | Q62: Audit logging | R62: 11. Monitoring & Audit
D63: 11.3 | E63: Alerting & SLA reporting | F63: DevOps Engineer | G63: 11.1 | H63: 18 | I63: 1 | J63: =EDATE(Charter!$D$11,$H63-1) -> 46844 | K63: =EDATE(Charter!$D$11,$H63-1+$I63)-1 -> 46873 | L63: ✓ | P63: Not started | Q63: Alerting & SLA | R63: 11. Monitoring & Audit
D64: 11.4 | E64: Data-privacy compliance review per country | F64: Security Lead | G64: 11.2 | H64: 18 | I64: 1 | J64: =EDATE(Charter!$D$11,$H64-1) -> 46844 | K64: =EDATE(Charter!$D$11,$H64-1+$I64)-1 -> 46873 | L64: ✓ | O64: ✓ | P64: Not started | Q64: Privacy sign-off | R64: 11. Monitoring & Audit
D65: 11.5 | E65: Monitoring & audit acceptance (GATE) | F65: QA Lead | G65: 11.3,11.4 | H65: 19 | I65: 1 | J65: =EDATE(Charter!$D$11,$H65-1) -> 46874 | K65: =EDATE(Charter!$D$11,$H65-1+$I65)-1 -> 46904 | L65: ✓ | P65: Not started | Q65: Monitoring accepted | R65: 11. Monitoring & Audit
B66: 4. UAT per region | C66: 12. UAT per region | D66: 12.1 | E66: UAT strategy, scripts & entry / exit criteria | F66: QA Lead | G66: 10.5 | H66: 17 | I66: 1 | J66: =EDATE(Charter!$D$11,$H66-1) -> 46813 | K66: =EDATE(Charter!$D$11,$H66-1+$I66)-1 -> 46843 | L66: ✓ | O66: ✓ | P66: Not started | Q66: UAT pack | R66: 12. UAT per region
D67: 12.2 | E67: UAT — South Africa (Wave 1 pilot) | F67: Country SME / QA Lead | G67: 12.1,11.5 | H67: 18 | I67: 1 | J67: =EDATE(Charter!$D$11,$H67-1) -> 46844 | K67: =EDATE(Charter!$D$11,$H67-1+$I67)-1 -> 46873 | L67: ✓ | O67: ✓ | P67: Not started | Q67: SA UAT sign-off | R67: 12. UAT per region
D68: 12.3 | E68: UAT — Nigeria & Kenya (Wave 2) | F68: Country SMEs | G68: 13.2 | H68: 20 | I68: 1 | J68: =EDATE(Charter!$D$11,$H68-1) -> 46905 | K68: =EDATE(Charter!$D$11,$H68-1+$I68)-1 -> 46934 | L68: ✓ | O68: ✓ | P68: Not started | Q68: NG & KE UAT sign-off | R68: 12. UAT per region
D69: 12.4 | E69: UAT — Ghana, Tanzania & Uganda (Wave 3) | F69: Country SMEs | G69: 13.4 | H69: 22 | I69: 1 | J69: =EDATE(Charter!$D$11,$H69-1) -> 46966 | K69: =EDATE(Charter!$D$11,$H69-1+$I69)-1 -> 46996 | L69: ✓ | O69: ✓ | P69: Not started | Q69: GH, TZ & UG UAT sign-off | R69: 12. UAT per region
B70: 5. Deployment per region | C70: 13. Deployment & Rollout | D70: 13.1 | E70: Wave 1 go-live — South Africa | F70: Country SME / PM | G70: 12.2 | H70: 19 | I70: 1 | J70: =EDATE(Charter!$D$11,$H70-1) -> 46874 | K70: =EDATE(Charter!$D$11,$H70-1+$I70)-1 -> 46904 | L70: ✓ | M70: ✓ | O70: ✓ | P70: Not started | Q70: SA in production | R70: 13. Deployment & Rollout
D71: 13.2 | E71: Wave 1 hypercare & stabilisation | F71: Programme Manager | G71: 13.1 | H71: 19 | I71: 1 | J71: =EDATE(Charter!$D$11,$H71-1) -> 46874 | K71: =EDATE(Charter!$D$11,$H71-1+$I71)-1 -> 46904 | L71: ✓ | O71: ✓ | P71: Not started | Q71: Wave 1 stabilised | R71: 13. Deployment & Rollout
D72: 13.3 | E72: Wave 2 go-live — Nigeria & Kenya | F72: Country SMEs | G72: 12.3 | H72: 21 | I72: 1 | J72: =EDATE(Charter!$D$11,$H72-1) -> 46935 | K72: =EDATE(Charter!$D$11,$H72-1+$I72)-1 -> 46965 | L72: ✓ | M72: ✓ | O72: ✓ | P72: Not started | Q72: NG & KE in production | R72: 13. Deployment & Rollout
D73: 13.4 | E73: Wave 2 hypercare | F73: Programme Manager | G73: 13.3 | H73: 21 | I73: 1 | J73: =EDATE(Charter!$D$11,$H73-1) -> 46935 | K73: =EDATE(Charter!$D$11,$H73-1+$I73)-1 -> 46965 | L73: ✓ | O73: ✓ | P73: Not started | Q73: Wave 2 stabilised | R73: 13. Deployment & Rollout
D74: 13.5 | E74: Wave 3 go-live — Ghana, Tanzania & Uganda | F74: Country SMEs | G74: 12.4 | H74: 23 | I74: 1 | J74: =EDATE(Charter!$D$11,$H74-1) -> 46997 | K74: =EDATE(Charter!$D$11,$H74-1+$I74)-1 -> 47026 | L74: ✓ | M74: ✓ | O74: ✓ | P74: Not started | Q74: GH, TZ & UG in production | R74: 13. Deployment & Rollout
D75: 13.6 | E75: Wave 3 hypercare | F75: Programme Manager | G75: 13.5 | H75: 23 | I75: 1 | J75: =EDATE(Charter!$D$11,$H75-1) -> 46997 | K75: =EDATE(Charter!$D$11,$H75-1+$I75)-1 -> 47026 | L75: ✓ | O75: ✓ | P75: Not started | Q75: Wave 3 stabilised | R75: 13. Deployment & Rollout
D76: 13.7 | E76: Programme close, benefits & handover to run | F76: Programme Manager | G76: 13.6 | H76: 24 | I76: 1 | J76: =EDATE(Charter!$D$11,$H76-1) -> 47027 | K76: =EDATE(Charter!$D$11,$H76-1+$I76)-1 -> 47057 | L76: ✓ | M76: ✓ | O76: ✓ | P76: Not started | Q76: Programme closure | R76: 13. Deployment & Rollout
B78: How to use: update only the Status column as work progresses, and the Mo. / Dur. columns if a task moves. Start and end dates recalculate automatically. GATE tasks are phase exit points — they need steering-committee sign-off before the next phase starts.

Sheet Timeline
B2: PROGRAMME TIMELINE · 24 MONTHS
B3: Phase bars and milestone markers are generated from the Project Plan and Milestones tabs.
E5: YEAR 1 | Q5: YEAR 2
E6: Q1 | H6: Q2 | K6: Q3 | N6: Q4 | Q6: Q1 | T6: Q2 | W6: Q3 | Z6: Q4
B7: Phase | C7: Start | D7: Finish | E7: =IF(Charter!$D$11="","",Charter!$D$11) -> 46327 | F7: =IF(E7="","",EDATE(E7,1)) -> 46357 | G7: =IF(F7="","",EDATE(F7,1)) -> 46388 | H7: =IF(G7="","",EDATE(G7,1)) -> 46419 | I7: =IF(H7="","",EDATE(H7,1)) -> 46447 | J7: =IF(I7="","",EDATE(I7,1)) -> 46478 | K7: =IF(J7="","",EDATE(J7,1)) -> 46508 | L7: =IF(K7="","",EDATE(K7,1)) -> 46539 | M7: =IF(L7="","",EDATE(L7,1)) -> 46569 | ... AB7: =IF(AA7="","",EDATE(AA7,1)) -> 47027
B8: 1. Africa Assessment | C8: =MIN('Project Plan'!$J$7:$J$12) -> 46327 | D8: =MAX('Project Plan'!$K$7:$K$12) -> 46418
B9: 2. Technical Discovery | C9: =MIN('Project Plan'!$J$13:$J$18) -> 46357 | D9: =MAX('Project Plan'!$K$13:$K$18) -> 46446
B10: 3. Documentation & Sign-off | C10: =MIN('Project Plan'!$J$19:$J$23) -> 46419 | D10: =MAX('Project Plan'!$K$19:$K$23) -> 46507
B11: 4. Foundation Integration Layer | C11: =MIN('Project Plan'!$J$24:$J$31) -> 46419 | D11: =MAX('Project Plan'!$K$24:$K$31) -> 46568
B12: 5. Client & Engagement Sync | C12: =MIN('Project Plan'!$J$32:$J$36) -> 46478 | D12: =MAX('Project Plan'!$K$32:$K$36) -> 46599
B13: 6. Trial Balance & GL Integration | C13: =MIN('Project Plan'!$J$37:$J$42) -> 46539 | D13: =MAX('Project Plan'!$K$37:$K$42) -> 46691
B14: 7. Document Synchronisation | C14: =MIN('Project Plan'!$J$43:$J$47) -> 46600 | D14: =MAX('Project Plan'!$K$43:$K$47) -> 46721
B15: 8. Status Synchronisation | C15: =MIN('Project Plan'!$J$48:$J$51) -> 46661 | D15: =MAX('Project Plan'!$K$48:$K$51) -> 46752
B16: 9. Comments & To-Do Sync | C16: =MIN('Project Plan'!$J$52:$J$55) -> 46692 | D16: =MAX('Project Plan'!$K$52:$K$55) -> 46783
B17: 10. Workflow Automation | C17: =MIN('Project Plan'!$J$56:$J$60) -> 46722 | D17: =MAX('Project Plan'!$K$56:$K$60) -> 46843
B18: 11. Monitoring & Audit | C18: =MIN('Project Plan'!$J$61:$J$65) -> 46784 | D18: =MAX('Project Plan'!$K$61:$K$65) -> 46904
B19: 12. UAT per region | C19: =MIN('Project Plan'!$J$66:$J$69) -> 46813 | D19: =MAX('Project Plan'!$K$66:$K$69) -> 46996
B20: 13. Deployment & Rollout | C20: =MIN('Project Plan'!$J$70:$J$76) -> 46874 | D20: =MAX('Project Plan'!$K$70:$K$76) -> 47057
B21: ◆ Milestones / gates | E21: =IF(COUNTIFS(Milestones!$F$7:$F$21,">="&E$7,Milestones!$F$7:$F$21,"<="&EOMONTH(E$7,0))>0,"◆","") | F21: =IF(COUNTIFS(Milestones!$F$7:$F$21,">="&F$7,Milestones!$F$7:$F$21,"<="&EOMONTH(F$7,0))>0,"◆","") | G21: =IF(COUNTIFS(Milestones!$F$7:$F$21,">="&G$7,Milestones!$F$7:$F$21,"<="&EOMONTH(G$7,0))>0,"◆","") -> ◆ | H21: =IF(COUNTIFS(Milestones!$F$7:$F$21,">="&H$7,Milestones!$F$7:$F$21,"<="&EOMONTH(H$7,0))>0,"◆","") -> ◆ | I21: =IF(COUNTIFS(Milestones!$F$7:$F$21,">="&I$7,Milestones!$F$7:$F$21,"<="&EOMONTH(I$7,0))>0,"◆","") | J21: =IF(COUNTIFS(Milestones!$F$7:$F$21,">="&J$7,Milestones!$F$7:$F$21,"<="&EOMONTH(J$7,0))>0,"◆","") -> ◆ | K21: =IF(COUNTIFS(Milestones!$F$7:$F$21,">="&K$7,Milestones!$F$7:$F$21,"<="&EOMONTH(K$7,0))>0,"◆","") | L21: =IF(COUNTIFS(Milestones!$F$7:$F$21,">="&L$7,Milestones!$F$7:$F$21,"<="&EOMONTH(L$7,0))>0,"◆","") -> ◆ | ... AB21: =IF(COUNTIFS(Milestones!$F$7:$F$21,">="&AB$7,Milestones!$F$7:$F$21,"<="&EOMONTH(AB$7,0))>0,"◆","") -> ◆
B23: Legend | D23: Phase active
C24: ◆ | D24: Milestone / gate month
D25: Current month

Sheet Milestones
B2: MILESTONES & PHASE GATES
B3: Target dates are calculated from the programme start date. A gate is a decision point with evidence, not a status update.
B6: ID | C6: Milestone | D6: Phase | E6: Month | F6: Target date | G6: Owner | H6: Status | I6: Acceptance criteria / evidence required
B7: MS-01 | C7: Assessment & prioritisation signed off | D7: 1. Africa Assessment | E7: M3 | F7: =EDATE(Charter!$D$11,3)-1 -> 46418 | G7: Programme Manager | H7: Not started | I7: Prioritised requirements and country scope approved by the steering committee
B8: MS-02 | C8: Architecture baseline approved | D8: 2. Technical Discovery | E8: M4 | F8: =EDATE(Charter!$D$11,4)-1 -> 46446 | G8: Solution Architect | H8: Not started | I8: Target architecture, security design and SyncAPI approach signed off
B9: MS-03 | C9: Stakeholder documentation signed off — all six countries | D9: 3. Documentation & Sign-off | E9: M6 | F9: =EDATE(Charter!$D$11,6)-1 -> 46507 | G9: Programme Manager | H9: Not started | I9: BRD, functional specification and privacy pack approved by tax, IT and vendors
B10: MS-04 | C10: Foundation layer ready | D10: 4. Foundation Integration Layer | E10: M8 | F10: =EDATE(Charter!$D$11,8)-1 -> 46568 | G10: Integration Lead | H10: Not started | I10: Agent, authentication, messaging and core connector pass integration test
B11: MS-05 | C11: Client & engagement sync complete | D11: 5. Client & Engagement Sync | E11: M9 | F11: =EDATE(Charter!$D$11,9)-1 -> 46599 | G11: QA Lead | H11: Not started | I11: Clients, users, engagements and periods synchronise reliably
B12: MS-06 | C12: TB / GL synchronisation validated | D12: 6. Trial Balance & GL Integration | E12: M12 | F12: =EDATE(Charter!$D$11,12)-1 -> 46691 | G12: Solution Architect | H12: Not started | I12: TB and GL sync end-to-end with reconciliation controls passing
B13: MS-07 | C13: Document sync complete | D13: 7. Document Synchronisation | E13: M13 | F13: =EDATE(Charter!$D$11,13)-1 -> 46721 | G13: QA Lead | H13: Not started | I13: Documents, schedules and packs synchronise with versioning
B14: MS-08 | C14: Status sync complete | D14: 8. Status Synchronisation | E14: M14 | F14: =EDATE(Charter!$D$11,14)-1 -> 46752 | G14: QA Lead | H14: Not started | I14: Bi-directional status updates verified
B15: MS-09 | C15: Comments & to-do sync complete | D15: 9. Comments & To-Do Sync | E15: M15 | F15: =EDATE(Charter!$D$11,15)-1 -> 46783 | G15: QA Lead | H15: Not started | I15: Comments, review notes, assignments and to-dos synchronise
B16: MS-10 | C16: Workflow automation complete | D16: 10. Workflow Automation | E16: M17 | F16: =EDATE(Charter!$D$11,17)-1 -> 46843 | G16: Solution Architect | H16: Not started | I16: Event-based automation with exception handling verified
B17: MS-11 | C17: Monitoring & audit accepted | D17: 11. Monitoring & Audit | E17: M19 | F17: =EDATE(Charter!$D$11,19)-1 -> 46904 | G17: QA Lead | H17: Not started | I17: Dashboards, audit trail, alerting and privacy review accepted
B18: MS-12 | C18: Wave 1 go-live — South Africa | D18: 13. Deployment & Rollout | E18: M19 | F18: =EDATE(Charter!$D$11,19)-1 -> 46904 | G18: Country SME / PM | H18: Not started | I18: SA pilot in production; hypercare exit criteria met
B19: MS-13 | C19: Wave 2 go-live — Nigeria & Kenya | D19: 13. Deployment & Rollout | E19: M21 | F19: =EDATE(Charter!$D$11,21)-1 -> 46965 | G19: Country SMEs | H19: Not started | I19: NG and KE in production; hypercare exit criteria met
B20: MS-14 | C20: Wave 3 go-live — Ghana, Tanzania & Uganda | D20: 13. Deployment & Rollout | E20: M23 | F20: =EDATE(Charter!$D$11,23)-1 -> 47026 | G20: Country SMEs | H20: Not started | I20: GH, TZ and UG in production; hypercare exit criteria met
B21: MS-15 | C21: Programme closure & handover to run | D21: 13. Deployment & Rollout | E21: M24 | F21: =EDATE(Charter!$D$11,24)-1 -> 47057 | G21: Programme Manager | H21: Not started | I21: Benefits realised, handover to run complete, programme closed

Sheet Risks
B2: RISK REGISTER
B3: Likelihood × impact, each scored 1–5. Score 15+ high · 8–14 medium · below 8 low.
B7: ID | C7: Category | D7: Risk | E7: L | F7: I | G7: Score | H7: Rating | I7: Mitigation / response | J7: Owner | K7: Status
B8: R-01 | C8: Vendor / Access | D8: SyncAPI access not granted or delayed by Silverfin, blocking TB / GL synchronisation | E8: 5 | F8: 5 | G8: =IF(OR($E8="",$F8=""),"",$E8*$F8) -> 25 | H8: =IF($G8="","",IF($G8>=15,"High",IF($G8>=8,"Medium","Low"))) -> High | I8: Raise a formal access request during discovery; secure a vendor SLA and escalation path; design a fallback TB import | J8: Integration Lead | K8: Open
B9: R-02 | C9: Technical | D9: Comments / To-Do (Remarks) APIs unsupported or limited bi-directionally | E9: 4 | F9: 3 | G9: =IF(OR($E9="",$F9=""),"",$E9*$F9) -> 12 | H9: =IF($G9="","",IF($G9>=15,"High",IF($G9>=8,"Medium","Low"))) -> Medium | I9: Early validation spike in Technical Discovery; agree a one-way fallback design if constrained | J9: Integration Engineer | K9: Open
B10: R-03 | C10: Data | D10: Trial-balance and chart-of-accounts mapping inconsistencies across the six countries | E10: 4 | F10: 4 | G10: =IF(OR($E10="",$F10=""),"",$E10*$F10) -> 16 | H10: =IF($G10="","",IF($G10>=15,"High",IF($G10>=8,"Medium","Low"))) -> High | I10: Account-mapping lists; transformation rules; reconciliation controls; per-country validation | J10: Data Specialist | K10: Open
B11: R-04 | C11: Compliance | D11: Data residency and privacy differences (POPIA, NDPA, Kenya / TZ / UG / GH DPAs) | E11: 3 | F11: 5 | G11: =IF(OR($E11="",$F11=""),"",$E11*$F11) -> 15 | H11: =IF($G11="","",IF($G11>=15,"High",IF($G11>=8,"Medium","Low"))) -> High | I11: Data Protection Impact Assessment; regional hosting; per-jurisdiction legal review | J11: Security Lead | K11: Open
B12: R-05 | C12: Scope | D12: Country-specific statutory and tax requirements expand scope | E12: 4 | F12: 3 | G12: =IF(OR($E12="",$F12=""),"",$E12*$F12) -> 12 | H12: =IF($G12="","",IF($G12>=15,"High",IF($G12>=8,"Medium","Low"))) -> Medium | I12: Change control; country prioritisation; MVP-first per market | J12: Programme Manager | K12: Open
B13: R-06 | C13: Resource | D13: Scarcity of Silverfin / Intela integration skills | E13: 4 | F13: 4 | G13: =IF(OR($E13="",$F13=""),"",$E13*$F13) -> 16 | H13: =IF($G13="","",IF($G13>=15,"High",IF($G13>=8,"Medium","Low"))) -> High | I13: Early staffing; vendor enablement; structured knowledge transfer; reuse of the architecture | J13: Programme Manager | K13: Open
B14: R-07 | C14: Dependency | D14: Intela Integration Agent maturity or feature limitations | E14: 3 | F14: 4 | G14: =IF(OR($E14="",$F14=""),"",$E14*$F14) -> 12 | H14: =IF($G14="","",IF($G14>=15,"High",IF($G14>=8,"Medium","Low"))) -> Medium | I14: Proof of concept; India CTR reference; vendor engagement on the roadmap | J14: Integration Lead | K14: Open
B15: R-08 | C15: Schedule | D15: 24-month multi-country rollout slips against plan | E15: 4 | F15: 4 | G15: =IF(OR($E15="",$F15=""),"",$E15*$F15) -> 16 | H15: =IF($G15="","",IF($G15>=15,"High",IF($G15>=8,"Medium","Low"))) -> High | I15: Wave-based rollout; critical-path management; phase-gate buffers; hypercare windows | J15: Programme Manager | K15: Open
B16: R-09 | C16: Performance | D16: API rate limits or performance degradation at scale | E16: 3 | F16: 3 | G16: =IF(OR($E16="",$F16=""),"",$E16*$F16) -> 9 | H16: =IF($G16="","",IF($G16>=15,"High",IF($G16>=8,"Medium","Low"))) -> Medium | I16: Batching and throttling; caching; load and volume testing before go-live | J16: Solution Architect | K16: Open
B17: R-10 | C17: Change | D17: Low practitioner adoption across countries | E17: 3 | F17: 4 | G17: =IF(OR($E17="",$F17=""),"",$E17*$F17) -> 12 | H17: =IF($G17="","",IF($G17>=15,"High",IF($G17>=8,"Medium","Low"))) -> Medium | I17: Change management; training; country champions; phased cut-over | J17: Change / Training Lead | K17: Open
B18: R-11 | C18: Security | D18: Credential and secret sprawl across environments and countries | E18: 3 | F18: 4 | G18: =IF(OR($E18="",$F18=""),"",$E18*$F18) -> 12 | H18: =IF($G18="","",IF($G18>=15,"High",IF($G18>=8,"Medium","Low"))) -> Medium | I18: Central vault; rotation; least privilege; secrets scanning in CI/CD | J18: Security Lead | K18: Open
B19: R-12 | C19: Quality | D19: Bi-directional sync conflicts — source-of-truth ambiguity | E19: 4 | F19: 4 | G19: =IF(OR($E19="",$F19=""),"",$E19*$F19) -> 16 | H19: =IF($G19="","",IF($G19>=15,"High",IF($G19>=8,"Medium","Low"))) -> High | I19: Define the system of record per data domain up front (see open question Q-01) | J19: Solution Architect | K19: Open
... B22: R-15 | C22: Operational | D22: Silent integration failures without monitoring | E22: 3 | F22: 4 | G22: =IF(OR($E22="",$F22=""),"",$E22*$F22) -> 12 | H22: =IF($G22="","",IF($G22>=15,"High",IF($G22>=8,"Medium","Low"))) -> Medium | I22: Observability, alerting and audit trail delivered in phase 11 | J22: DevOps Engineer | K22: Open
B24: SCORING GUIDE
B25: 1 – 7 | D25: Low | E25: Accept and monitor at the fortnightly review.
B26: 8 – 14 | D26: Medium | E26: Named owner and a dated response; reviewed monthly.
B27: 15 – 25 | D27: High | E27: Escalate to the sponsor within 48 hours; reviewed at every checkpoint.

Sheet Dependencies
B2: DEPENDENCIES, ASSUMPTIONS & OPEN QUESTIONS
B3: What the programme relies on but does not control, and what must be resolved during discovery.
B6: ID | C6: Type | D6: Dependency | E6: Description | F6: Needed by | G6: Owner | H6: Status
B7: D-01 | C7: Vendor | D7: Silverfin SyncAPI access | E7: Access to SyncAPI to synchronise trial balance and general ledger — the critical-path dependency | F7: Phase 6 (by M8) | G7: Integration Lead | H7: Open
B8: D-02 | C8: Vendor | D8: Intela Integration Agent | E8: Availability and configuration of the strategic integration mechanism | F8: Phase 4 (by M4) | G8: Integration Lead | H8: Open
B9: D-03 | C9: Internal | D9: India CTR reference | E9: Access to India CTR documentation and team for the reference architecture | F9: Phase 2 (by M3) | G9: Solution Architect | H9: Open
B10: D-04 | C10: Vendor | D10: Silverfin API credentials | E10: API credentials per country / firm environment | F10: Phase 4 (by M5) | G10: Security Lead | H10: Open
B11: D-05 | C11: Internal | D11: Country SME availability | E11: Part-time tax SMEs for all six countries throughout the programme | F11: Phase 1 onward | G11: Country Leads | H11: Open
B12: D-06 | C12: Internal | D12: Cloud tenancy & environments | E12: Provisioning of dev / test / UAT / prod meeting data-residency needs | F12: Phase 4 (by M4) | G12: DevOps Engineer | H12: Open
B13: D-07 | C13: Internal | D13: Data-privacy sign-off | E13: Per-jurisdiction privacy approval (POPIA, NDPA and others) | F13: Phase 3 & 11 | G13: Security Lead | H13: Open
B14: D-08 | C14: Internal | D14: Client CoA & mapping data | E14: Charts of accounts and mapping source data per client | F14: Phase 5–6 (by M7) | G14: Data Specialist | H14: Open
B15: D-09 | C15: Vendor | D15: Silverfin licensing | E15: Confirmed Silverfin licensing for each country in scope | F15: Phase 1 (by M3) | G15: Programme Manager | H15: Open
B16: D-10 | C16: Internal | D16: Change & training resource | E16: Change-management and training capacity for rollout | F16: Rollout (M18+) | G16: Change / Training Lead | H16: Open
B18: PLANNING ASSUMPTIONS
B19: ID | C19: Assumption | F19: Impact if invalid | G19: Owner | H19: Status
B20: A-01 | C20: Silverfin SyncAPI is available under Deloitte licensing and access will be granted | F20: Blocks TB / GL sync; re-plan phase 6 | G20: Integration Lead | H20: To confirm
B21: A-02 | C21: The Intela Integration Agent is the strategic integration mechanism | F21: Architecture rework | G21: Solution Architect | H21: To confirm
B22: A-03 | C22: The India CTR integration is available as a reference pattern | F22: Slower discovery; more design effort | G22: Solution Architect | H22: To confirm
B23: A-04 | C23: Cloud tenancy can meet each country's data-residency needs | F23: Hosting redesign; compliance risk | G23: Security Lead | H23: To confirm
B24: A-05 | C24: Country SMEs are available part-time throughout the programme | F24: Requirements and rollout delays | G24: Programme Manager | H24: To confirm
B25: A-06 | C25: Bi-directional sync is required and the system of record is confirmed per data domain | F25: Sync conflicts (see R-12) | G25: Solution Architect | H25: To confirm
B26: A-07 | C26: Budget and resourcing are approved for a 24-month programme | F26: Scope or timeline reduction | G26: Sponsor | H26: To confirm
B28: OPEN QUESTIONS — to resolve in discovery
B29: ID | C29: Question | F29: Why it matters | G29: Owner | H29: Status
B30: Q-01 | C30: Source of truth — which platform is the system of record for each data domain? | F30: Determines bi-directional sync design and conflict rules | G30: Solution Architect | H30: Open
B31: Q-02 | C31: SyncAPI access — how is it provisioned; what are the timelines, cost and per-country implications? | F31: Critical-path dependency for TB / GL | G31: Integration Lead | H31: Open
B32: Q-03 | C32: Comments API — are Remarks / Comments and to-do fully supported bi-directionally? | F32: Confirms phase 9 scope and fallback | G32: Integration Engineer | H32: Open
B33: Q-04 | C33: TB import APIs — confirmed endpoints, formats and volume limits? | F33: Drives TB integration design and performance | G33: Data Specialist | H33: Open
B34: Q-05 | C34: Country-specific requirements — statutory and tax differences affecting mapping? | F34: Scope, mapping and rollout sequencing | G34: Country SMEs | H34: Open
B35: Q-06 | C35: Rollout priorities — confirm country sequencing and the South Africa pilot? | F35: Locks the wave plan and schedule | G35: Programme Manager | H35: Open

Sheet Country Rollout
B2: COUNTRY ASSESSMENT & ROLLOUT WAVES
B3: Readiness across the six markets and the wave sequencing that follows from it.
B6: Country | C6: Practice maturity | D6: Silverfin adoption | E6: Data-privacy regime | F6: Complexity | G6: Wave | H6: Priority | I6: Notes
B7: South Africa | C7: High | D7: High | E7: POPIA | F7: Medium | G7: Wave 1 | H7: Pilot | I7: Largest Deloitte Africa tax practice; strongest Silverfin base; closest to the target operating model
B8: Nigeria | C8: High | D8: Medium | E8: NDPA / NDPR | F8: High | G8: Wave 2 | H8: High | I8: Strong local team; active Nigeria Tax Act 2025 work; high statutory complexity
B9: Kenya | C9: Medium | D9: Medium | E9: Kenya DPA 2019 | F9: Medium | G9: Wave 2 | H9: High | I9: East-Africa hub; regional coordination point
B10: Ghana | C10: Medium | D10: Low | E10: DPA 2012 | F10: Medium | G10: Wave 3 | H10: Medium | I10: West-Africa rollout; requires enablement uplift
B11: Tanzania | C11: Low | D11: Low | E11: PDPA 2022 | F11: Medium | G11: Wave 3 | H11: Medium | I11: Lower current adoption; standardise on the established pattern
B12: Uganda | C12: Low | D12: Low | E12: DPPA 2019 | F12: Medium | G12: Wave 3 | H12: Medium | I12: Lower current adoption; leverage East-Africa learnings
B14: ROLLOUT WAVES
B15: Wave | C15: Countries | D15: Months | E15: Scope | H15: Entry criteria | I15: Exit / go-live criteria
B16: Wave 0 | C16: Build & pilot preparation (all countries) | D16: M1–M17 | E16: Foundation layer plus all integration modules (client, TB / GL, documents, status, comments, workflow, monitoring) | H16: Charter approved; SyncAPI access and architecture baseline confirmed | I16: All modules pass integration testing; UAT scripts ready
B17: Wave 1 | C17: South Africa (pilot) | D17: M18–M19 | E17: Full solution pilot in the most mature market | H17: Wave 0 complete; monitoring and audit accepted; SA environment ready | I17: SA in production; reconciliation clean; hypercare exit met
B18: Wave 2 | C18: Nigeria, Kenya | D18: M20–M21 | E18: Country configuration, UAT and go-live for NG and KE | H18: Wave 1 stabilised; country requirements and mappings confirmed | I18: NG and KE in production; hypercare exit met
B19: Wave 3 | C19: Ghana, Tanzania, Uganda | D19: M22–M24 | E19: Country configuration, UAT and go-live for GH, TZ and UG; programme closure | H19: Wave 2 stabilised; enablement and training complete | I19: All six countries live; benefits realised; handover to run
